view_spark_timeline-0.2.9.dist-info/DESCRIPTION.rst
view_spark_timeline-0.2.9.dist-info/METADATA
view_spark_timeline-0.2.9.dist-info/RECORD
view_spark_timeline-0.2.9.dist-info/WHEEL
view_spark_timeline-0.2.9.dist-info/entry_points.txt
view_spark_timeline-0.2.9.dist-info/metadata.json
view_spark_timeline-0.2.9.dist-info/top_level.txt
viewsparktimeline/__init__.py
viewsparktimeline/__main__.py
viewsparktimeline/cli.py
viewsparktimeline/exceptions.py
viewsparktimeline/generator.py
viewsparktimeline/outputs.py
viewsparktimeline/utils.py
viewsparktimeline/version.py
