Metadata-Version: 2.0
Name: view-spark-timeline
Version: 0.2.9
Summary: Command line application to visualize the timeline of Spark executions.
Home-page: https://github.com/fpoli/view-spark-timeline
Author: Federico Poli
Author-email: federpoli@gmail.com
License: MIT
Platform: UNKNOWN
Classifier: Development Status :: 4 - Beta
Classifier: Environment :: Console
Classifier: License :: OSI Approved :: MIT License
Classifier: Programming Language :: Python :: 3
Classifier: Programming Language :: Python :: 3.5
Requires-Dist: svgwrite (==1.1.11)
Requires-Dist: ujson (==1.35)
Provides-Extra: dev
Requires-Dist: nose (==1.3.7); extra == 'dev'
Requires-Dist: pycodestyle (==2.3.1); extra == 'dev'
Requires-Dist: twine (==1.9.1); extra == 'dev'
